jjowl/_.pdf
jjowl/__init__.py
jjowl/jjowl.py
jjowl/ont_convert.py
jjowl/reindent.py
jjowl-0.2.18.dist-info/entry_points.txt
jjowl-0.2.18.dist-info/WHEEL
jjowl-0.2.18.dist-info/METADATA
jjowl-0.2.18.dist-info/RECORD
