Metadata-Version: 2.1
Name: jjowl
Version: 0.2.18
Summary: VERY EXPERIMENTAL :  module for opinied command line processing of OWL ontologies
Author-email: JJoao <jj@di.uminho.pt>
Classifier: License :: OSI Approved :: MIT License
Requires-Dist: rdflib
Requires-Dist: jjcli
Requires-Dist: owlrl
Requires-Dist: unidecode
Requires-Dist: pyyaml
Project-URL: Home, https://natura.di.uminho.pt/jjowl
